gaussiancl.py
gaussiancl-2023.1.dist-info/LICENSE
gaussiancl-2023.1.dist-info/METADATA
gaussiancl-2023.1.dist-info/WHEEL
gaussiancl-2023.1.dist-info/top_level.txt
gaussiancl-2023.1.dist-info/RECORD
