Metadata-Version: 2.1
Name: gaussiancl
Version: 2023.1
Summary: angular power spectra for transformed Gaussian random fields
Home-page: https://github.com/cltools/gaussiancl
Maintainer: Nicolas Tessore
Maintainer-email: n.tessore@ucl.ac.uk
License: MIT
Project-URL: Documentation, https://cltools.readthedocs.io/gaussiancl/
Classifier: Programming Language :: Python :: 3
Classifier: License :: OSI Approved :: MIT License
Classifier: Operating System :: OS Independent
Requires-Python: >=3.6
License-File: LICENSE
Requires-Dist: numpy
Requires-Dist: transformcl (>=2022.7.28)
